openedx_rest_api_client/__init__.py
openedx_rest_api_client/__version__.py
openedx_rest_api_client/auth.py
openedx_rest_api_client/cached_token.py
openedx_rest_api_client/client.py
openedx_rest_api_client/exceptions.py
openedx_rest_api_client/session.py
openedx_rest_api_client-1.0.0.dist-info/LICENSE
openedx_rest_api_client-1.0.0.dist-info/METADATA
openedx_rest_api_client-1.0.0.dist-info/WHEEL
openedx_rest_api_client-1.0.0.dist-info/top_level.txt
openedx_rest_api_client-1.0.0.dist-info/RECORD
