Metadata-Version: 2.1
Name: openedx-rest-api-client
Version: 1.0.0
Summary: Standalone client used to access Open edX REST APIs.
Home-page: https://github.com/aulasneo/openedx-rest-api-client
Author: Aulasneo
Author-email: andres@aulasneo.com
License: Apache
Keywords: openedx rest api client
Classifier: Development Status :: 5 - Production/Stable
Classifier: License :: OSI Approved :: Apache Software License
Classifier: Programming Language :: Python
Classifier: Programming Language :: Python :: 3.8
Classifier: Topic :: Internet
Classifier: Intended Audience :: Developers
Classifier: Environment :: Web Environment
License-File: LICENSE
Requires-Dist: charset-normalizer==3.4.1
Requires-Dist: certifi==2024.12.14
Requires-Dist: urllib3==2.3.0
Requires-Dist: requests-toolbelt==1.0.0
Requires-Dist: idna==3.10
Requires-Dist: requests==2.32.3
